eoddata_client/__init__.py
eoddata_client/business_entities.py
eoddata_client/eoddata_client.py
eoddata_client/utils.py
eoddata_client-0.3.3.dist-info/DESCRIPTION.rst
eoddata_client-0.3.3.dist-info/METADATA
eoddata_client-0.3.3.dist-info/RECORD
eoddata_client-0.3.3.dist-info/WHEEL
eoddata_client-0.3.3.dist-info/metadata.json
eoddata_client-0.3.3.dist-info/top_level.txt
