Metadata-Version: 2.0
Name: eoddata-client
Version: 0.3.3
Summary: Client to get historical market data from EODData web service.
Home-page: https://github.com/apologist/eoddata-client
Author: Aleksey
Author-email: quant@apologist.io
License: Public Domain
Requires-Dist: pandas
Requires-Dist: requests
